[
  {
    "name": "MoreCulture25",
    "cost": 0,
    "uniques": [
      "Unbuildable <for [AI player]>",
      "culture": 25 ]
  },
	
  {
    "name": "MoreFaith25",
    "cost": 0,
    "uniques": [
      "Unbuildable <for [AI player]>",
      "faith": 25 ]
  },
	
  {
    "name": "MoreScience15",
    "cost": 0,
    "uniques": [
      "Unbuildable <for [AI player]>",
      "science": 15 ]
  },
	
  {
    "name": "MoreFood20",
    "cost": 0,
    "uniques": [
      "Unbuildable <for [AI player]>",
      "food": 20 ]
    }
  ]
